blp_helpers_data_science/__init__.py
blp_helpers_data_science/helper_time_series.py
blp_helpers_data_science/helpers_azure.py
blp_helpers_data_science/helpers_extract.py
blp_helpers_data_science/helpers_misc.py
blp_helpers_data_science/helpers_mongodb.py
blp_helpers_data_science/helpers_newsapi.py
blp_helpers_data_science/helpers_text.py
blp_helpers_data_science-3.0.2.dist-info/LICENSE
blp_helpers_data_science-3.0.2.dist-info/METADATA
blp_helpers_data_science-3.0.2.dist-info/WHEEL
blp_helpers_data_science-3.0.2.dist-info/top_level.txt
blp_helpers_data_science-3.0.2.dist-info/RECORD
