Metadata-Version: 2.1
Name: blp-helpers-data-science
Version: 3.0.2
Summary: Helpers I use for Data Science projects
Home-page: https://github.com/leugh/helpers_data_science
Author: Leopold Bosankic
Author-email: leopold.bosankic@outlook.com
Classifier: Programming Language :: Python :: 3
Classifier: License :: OSI Approved :: MIT License
Classifier: Operating System :: OS Independent
Requires-Python: >=3.6
License-File: LICENSE
